{
  "2026-07-06_-OwpQqbUQ2-zImFBi0Dl.jpeg": {
    "por": "ROTA",
    "em": "2026-07-06T03:18:41.968Z",
    "dia": "2026-07-06",
    "atrasada": true
  },
  "2026-07-06_-OwpQqhHWlF9aw-VQJJ6.jpeg": {
    "por": "ROTA",
    "em": "2026-07-06T03:18:42.339Z",
    "dia": "2026-07-06",
    "atrasada": true
  },
  "2026-07-06_-OwpQqlIltHxT92BoySA.jpeg": {
    "por": "ROTA",
    "em": "2026-07-06T03:18:42.596Z",
    "dia": "2026-07-06",
    "atrasada": true
  },
  "2026-07-06_-OwpQqp6MPMk5uTH6n64.jpeg": {
    "por": "ROTA",
    "em": "2026-07-06T03:18:42.840Z",
    "dia": "2026-07-06",
    "atrasada": true
  },
  "2026-07-06_-OwpQqsx2pAoT2ohm_Zh.jpeg": {
    "por": "ROTA",
    "em": "2026-07-06T03:18:43.085Z",
    "dia": "2026-07-06",
    "atrasada": true
  },
  "2026-07-06_-OwpQqwU5lfk2wBOxtZM.jpeg": {
    "por": "ROTA",
    "em": "2026-07-06T03:18:43.312Z",
    "dia": "2026-07-06",
    "atrasada": true
  },
  "2026-07-08_-Ox-AgIF1FeHdngZvMhl.jpeg": {
    "por": "ROTA",
    "em": "2026-07-08T05:23:54.745Z",
    "dia": "2026-07-08",
    "atrasada": false
  },
  "2026-07-08_-Ox-AgU8bDVrLeFIjyCe.jpeg": {
    "por": "ROTA",
    "em": "2026-07-08T05:23:55.506Z",
    "dia": "2026-07-08",
    "atrasada": false
  },
  "2026-07-08_-Ox-AgZ7OZu84Kv1j32g.jpeg": {
    "por": "ROTA",
    "em": "2026-07-08T05:23:55.826Z",
    "dia": "2026-07-08",
    "atrasada": false
  }
}